MANIFEST.in
README.md
setup.cfg
setup.py
KEP/KEP.py
KEP/__init__.py
KEP/cite.txt
KEP.egg-info/PKG-INFO
KEP.egg-info/SOURCES.txt
KEP.egg-info/dependency_links.txt
KEP.egg-info/top_level.txt
KEP/XMLcollection1/PMC8499788.xml
KEP/XMLcollection1/PMC8755319.xml
KEP/XMLcollection1/PMC8934712.xml
KEP/XMLcollection1/PMC9242688.xml
KEP/XMLcollection1/PMC9242884.xml
KEP/XMLcollection1/PMC9277988.xml
KEP/XMLcollection1/PMC9278083.xml
KEP/XMLcollection1/PMC9278178.xml
KEP/XMLcollection1/PMC9281458.xml
KEP/XMLcollection1/PMC9281590.xml
KEP/XMLcollection1/PMC9283122.xml
KEP/XMLcollection1/PMC9284567.xml
KEP/XMLcollection1/PMC9284599.xml
KEP/XMLcollection1/PMC9285112.xml
KEP/XMLcollection1/PMC9287470.xml
KEP/XMLcollection1/PMC9289581.xml
KEP/XMLcollection1/PMC9289664.xml
KEP/XMLcollection1/PMC9290425.xml
KEP/XMLcollection1/PMC9291241.xml
KEP/XMLcollection1/PMC9295334.xml
KEP/XMLcollection1/PMC9295375.xml
KEP/XMLcollection1/PMC9295384.xml
KEP/XMLcollection1/PMC9295679.xml
KEP/XMLcollection1/PMC9296900.xml
KEP/XMLcollection1/PMC9298167.xml
KEP/XMLcollection1/PMC9298468.xml
KEP/XMLcollection1/PMC9298551.xml
KEP/XMLcollection1/PMC9298711.xml
KEP/XMLcollection1/PMC9302868.xml
KEP/XMLcollection1/PMC9307220.xml
KEP/XMLcollection1/PMC9308500.xml
KEP/XMLcollection1/PMC9308998.xml
KEP/XMLcollection1/PMC9309232.xml
KEP/XMLcollection1/PMC9310363.xml
KEP/XMLcollection1/PMC9311342.xml
KEP/XMLcollection1/PMC9312374.xml
KEP/XMLcollection1/PMC9312732.xml
KEP/XMLcollection1/PMC9312909.xml
KEP/XMLcollection1/PMC9313162.xml
KEP/XMLcollection1/PMC9313938.xml
KEP/XMLcollection1/PMC9314237.xml
KEP/XMLcollection1/PMC9315516.xml
KEP/XMLcollection1/PMC9322618.xml
KEP/XMLcollection1/PMC9325633.xml
KEP/XMLcollection1/PMC9326076.xml
KEP/XMLcollection1/PMC9326230.xml
KEP/XMLcollection1/PMC9326243.xml
KEP/XMLcollection1/PMC9326247.xml
KEP/XMLcollection1/PMC9326261.xml
KEP/XMLcollection1/PMC9327186.xml
KEP/XMLcollection1/PMC9327440.xml
KEP/XMLcollection1/PMC9328125.xml
KEP/XMLcollection1/PMC9328743.xml
KEP/XMLcollection1/PMC9328841.xml
KEP/XMLcollection1/PMC9329529.xml
KEP/XMLcollection1/PMC9329661.xml
