Metadata-Version: 2.1
Name: KEP
Version: 1.0.0
Summary: UNKNOWN
Home-page: https://www.math.msstate.edu/directory/jshi
Author: Jingyi (Catherine) Shi & students
Author-email: jshi@math.msstate.edu
License: MIT
Keywords: COVID-19 Publications,Natural Language Processing,Named Entity Recognition,Key Topics,Disease Mentions,Locations,Weighted TF-IDF,Knowledge Extraction and Representation
Platform: UNKNOWN
